odoo8_addon_geoengine_sale-8.0.0.1.0.99.dev10-py2.7-nspkg.pth
odoo8_addon_geoengine_sale-8.0.0.1.0.99.dev10.dist-info/DESCRIPTION.rst
odoo8_addon_geoengine_sale-8.0.0.1.0.99.dev10.dist-info/METADATA
odoo8_addon_geoengine_sale-8.0.0.1.0.99.dev10.dist-info/RECORD
odoo8_addon_geoengine_sale-8.0.0.1.0.99.dev10.dist-info/WHEEL
odoo8_addon_geoengine_sale-8.0.0.1.0.99.dev10.dist-info/metadata.json
odoo8_addon_geoengine_sale-8.0.0.1.0.99.dev10.dist-info/namespace_packages.txt
odoo8_addon_geoengine_sale-8.0.0.1.0.99.dev10.dist-info/top_level.txt
odoo_addons/geoengine_sale/README.rst
odoo_addons/geoengine_sale/__init__.py
odoo_addons/geoengine_sale/__openerp__.py
odoo_addons/geoengine_sale/geo_sale.py
odoo_addons/geoengine_sale/geo_sale_view.xml
odoo_addons/geoengine_sale/i18n/ca.po
odoo_addons/geoengine_sale/i18n/de.po
odoo_addons/geoengine_sale/i18n/es.po
odoo_addons/geoengine_sale/i18n/es_ES.po
odoo_addons/geoengine_sale/i18n/fi.po
odoo_addons/geoengine_sale/i18n/fr.po
odoo_addons/geoengine_sale/i18n/hr.po
odoo_addons/geoengine_sale/i18n/hu.po
odoo_addons/geoengine_sale/i18n/it.po
odoo_addons/geoengine_sale/i18n/nl.po
odoo_addons/geoengine_sale/i18n/pt_BR.po
odoo_addons/geoengine_sale/i18n/ro.po
odoo_addons/geoengine_sale/i18n/sl.po
odoo_addons/geoengine_sale/i18n/tr.po
odoo_addons/geoengine_sale/i18n/tr_TR.po
odoo_addons/geoengine_sale/i18n/zh_CN.po
odoo_addons/geoengine_sale/static/description/icon.png
